simple_tensorflow_serving/__init__.py
simple_tensorflow_serving/abstract_inference_service.py
simple_tensorflow_serving/abstract_inference_service_test.py
simple_tensorflow_serving/base64_util.py
simple_tensorflow_serving/base64_util_test.py
simple_tensorflow_serving/client.py
simple_tensorflow_serving/filesystem_util.py
simple_tensorflow_serving/h2o_inference_service.py
simple_tensorflow_serving/mxnet_inference_service.py
simple_tensorflow_serving/onnx_inference_service.py
simple_tensorflow_serving/pmml_inference_service.py
simple_tensorflow_serving/preprocess_util.py
simple_tensorflow_serving/python_predict_client.py
simple_tensorflow_serving/scikitlearn_inference_service.py
simple_tensorflow_serving/server.py
simple_tensorflow_serving/tensorflow_inference_service.py
simple_tensorflow_serving/test.py
simple_tensorflow_serving/wsgi.py
simple_tensorflow_serving/xgboost_inference_service.py
simple_tensorflow_serving/gen_client/__init__.py
simple_tensorflow_serving/gen_client/gen_bash.py
simple_tensorflow_serving/gen_client/gen_client.py
simple_tensorflow_serving/gen_client/gen_golang.py
simple_tensorflow_serving/gen_client/gen_javascript.py
simple_tensorflow_serving/gen_client/gen_python.py
simple_tensorflow_serving/service_utils/__init__.py
simple_tensorflow_serving/service_utils/request_util.py
simple_tensorflow_serving/static/1.jpg
simple_tensorflow_serving/static/4.jpg
simple_tensorflow_serving/static/Mew.png
simple_tensorflow_serving/static/Screen Shot 2018-05-09 at 4.56.25 PM.png
simple_tensorflow_serving/static/cat.jpeg
simple_tensorflow_serving/static/dog3.jpeg
simple_tensorflow_serving/static/image104.jpg
simple_tensorflow_serving/static/bootstrap-4.0.0-dist/.DS_Store
simple_tensorflow_serving/static/bootstrap-4.0.0-dist/css/bootstrap-grid.css
simple_tensorflow_serving/static/bootstrap-4.0.0-dist/css/bootstrap-grid.css.map
simple_tensorflow_serving/static/bootstrap-4.0.0-dist/css/bootstrap-grid.min.css
simple_tensorflow_serving-0.6.4.dist-info/METADATA
simple_tensorflow_serving-0.6.4.dist-info/RECORD
simple_tensorflow_serving-0.6.4.dist-info/WHEEL
simple_tensorflow_serving-0.6.4.dist-info/entry_points.txt
simple_tensorflow_serving-0.6.4.dist-info/top_level.txt
